odoo/addons/pricelist_brand/README.rst
odoo/addons/pricelist_brand/__init__.py
odoo/addons/pricelist_brand/__manifest__.py
odoo/addons/pricelist_brand/i18n/pricelist_brand.pot
odoo/addons/pricelist_brand/models/__init__.py
odoo/addons/pricelist_brand/models/product_pricelist.py
odoo/addons/pricelist_brand/readme/CONTRIBUTORS.rst
odoo/addons/pricelist_brand/readme/DESCRIPTION.rst
odoo/addons/pricelist_brand/readme/USAGE.rst
odoo/addons/pricelist_brand/static/description/icon.png
odoo/addons/pricelist_brand/static/description/index.html
odoo/addons/pricelist_brand/tests/__init__.py
odoo/addons/pricelist_brand/tests/test_product_pricelist.py
odoo/addons/pricelist_brand/views/product_pricelist.xml
odoo13_addon_pricelist_brand-13.0.1.0.1.dev3.dist-info/METADATA
odoo13_addon_pricelist_brand-13.0.1.0.1.dev3.dist-info/WHEEL
odoo13_addon_pricelist_brand-13.0.1.0.1.dev3.dist-info/top_level.txt
odoo13_addon_pricelist_brand-13.0.1.0.1.dev3.dist-info/RECORD
